MANIFEST.in
README.md
setup.py
dataset/pre_processing/pre_processor.cpp
dermatillo/__init__.py
dermatillo/behavior_classification.py
dermatillo/benchmark.py
dermatillo/cli.py
dermatillo/config.py
dermatillo/face_detection.py
dermatillo/features_extraction.py
dermatillo/objects.py
dermatillo/observation.py
dermatillo/people_tracking.py
dermatillo/platforms.py
dermatillo/run.py
dermatillo/utils.py
dermatillo/video_capture.py
dermatillo.egg-info/PKG-INFO
dermatillo.egg-info/SOURCES.txt
dermatillo.egg-info/dependency_links.txt
dermatillo.egg-info/entry_points.txt
dermatillo.egg-info/requires.txt
dermatillo.egg-info/top_level.txt
dermatillo/files/LICENSE
dermatillo/files/behavior_classifier.tflite
dermatillo/files/config.json
requirements/dermatillo.txt